satellitepy-0.1.1.dist-info/METADATA
satellitepy-0.1.1.dist-info/WHEEL
satellitepy/__init__.py
satellitepy-0.1.1.dist-info/RECORD
