Metadata-Version: 2.1
Name: satellitepy
Version: 0.1.1
Summary: fastapi util
Author-Email: misilelaboratory <misileminecord@gmail.com>
License: MisileLab License
Requires-Python: >=3.12
Requires-Dist: fastapi==0.111.0
